simplebeam/__init__.py
simplebeam/beam.py
simplebeam/exceptions.py
simplebeam/loads.py
simplebeam/restraints.py
simplebeam-0.0.7.dist-info/LICENSE
simplebeam-0.0.7.dist-info/WHEEL
simplebeam-0.0.7.dist-info/METADATA
simplebeam-0.0.7.dist-info/RECORD
