Metadata-Version: 2.1
Name: simplebeam
Version: 0.0.7
Summary: Basic package for doing beam bending analysis.
Author-email: Sean Kane <mail@ifitsmoving.com>
Requires-Python: >=3.10
Classifier: License :: OSI Approved :: MIT License
Requires-Dist: sympy
Requires-Dist: numpy
Requires-Dist: matplotlib
Requires-Dist: rich
Requires-Dist: black ; extra == "dev"
Requires-Dist: isort ; extra == "dev"
Requires-Dist: coverage ; extra == "dev"
Requires-Dist: mypy ; extra == "dev"
Requires-Dist: pylint ; extra == "dev"
Requires-Dist: pytest ; extra == "dev"
Requires-Dist: ruff ; extra == "dev"
Project-URL: Home, https://github.com/skane88/simplebeam
Provides-Extra: dev
